kmeans_color_palette/__init__.py
kmeans_color_palette/about.py
kmeans_color_palette/desktop.py
kmeans_color_palette/program.py
kmeans_color_palette/icons/check.svg
kmeans_color_palette/icons/logo.png
kmeans_color_palette/modules/__init__.py
kmeans_color_palette/modules/color.py
kmeans_color_palette/modules/configure.py
kmeans_color_palette/modules/wabout.py
kmeans_color_palette-0.1.2.dist-info/licenses/LICENSE
kmeans_color_palette-0.1.2.dist-info/METADATA
kmeans_color_palette-0.1.2.dist-info/WHEEL
kmeans_color_palette-0.1.2.dist-info/entry_points.txt
kmeans_color_palette-0.1.2.dist-info/top_level.txt
kmeans_color_palette-0.1.2.dist-info/RECORD
