Metadata-Version: 2.4
Name: kmeans_color_palette
Version: 0.1.2
Summary: Color palette generator using the k-means algorithm.
Author-email: Fernando Pujaico Rivera <fernando.pujaico.rivera@gmail.com>
Maintainer-email: Fernando Pujaico Rivera <fernando.pujaico.rivera@gmail.com>
License-Expression: GPL-3.0-only WITH Classpath-exception-2.0 OR BSD-3-Clause
Project-URL: Bug Reports, https://github.com/trucomanx/KMeansColorPalette/issues
Project-URL: Funding, https://trucomanx.github.io/en/funding.html
Project-URL: Documentation, https://github.com/trucomanx/KMeansColorPalette/tree/main/doc
Project-URL: Source, https://github.com/trucomanx/KMeansColorPalette
Keywords: writing,translate
Classifier: Programming Language :: Python :: 3
Classifier: Operating System :: OS Independent
Requires-Python: >=3.8
License-File: LICENSE
Requires-Dist: PyQt5
Requires-Dist: scikit-learn
Requires-Dist: numpy
Requires-Dist: Pillow
Requires-Dist: opencv-python
Dynamic: license-file
